Metadata-Version: 1.1
Name: sphinx-execute-code
Version: 0.2a2
Summary: Sphinx support for execution of python code from code blocks or files
Home-page: https://github.com/jpsenior/sphinx-execute-code
Author: JP Senior
Author-email: jp.senior@gmail.com
License: MIT
Keywords: sphinx extension directive execute code
Platform: any
Classifier: Development Status :: 3 - Alpha
Classifier: Intended Audience :: Developers
Classifier: Framework :: Sphinx :: Extension
Classifier: License :: OSI Approved :: MIT License
Classifier: Natural Language :: English
Classifier: Programming Language :: Python :: 2.7
